{
    "os": "Linux-6.5.0-35-generic-x86_64-with-glibc2.35",
    "python": "3.11.0rc1",
    "heartbeatAt": "2024-06-04T16:29:23.267373",
    "startedAt": "2024-06-04T16:29:22.659882",
    "docker": null,
    "cuda": null,
    "args": [],
    "state": "running",
    "program": "/home/pedro/PINN/jaxpi/examples/geomI_2ph/main.py",
    "codePathLocal": "main.py",
    "codePath": "main.py",
    "host": "8b460e7a0fb5",
    "username": "root",
    "executable": "/usr/bin/python3",
    "cpu_count": 24,
    "cpu_count_logical": 32,
    "cpu_freq": {
        "current": 1700.25140625,
        "min": 800.0,
        "max": 4937.5
    },
    "cpu_freq_per_core": [
        {
            "current": 4901.387,
            "min": 800.0,
            "max": 5500.0
        },
        {
            "current": 800.0,
            "min": 800.0,
            "max": 5500.0
        },
        {
            "current": 800.0,
            "min": 800.0,
            "max": 5500.0
        },
        {
            "current": 3168.956,
            "min": 800.0,
            "max": 5500.0
        },
        {
            "current": 800.0,
            "min": 800.0,
            "max": 5500.0
        },
        {
            "current": 800.0,
            "min": 800.0,
            "max": 5500.0
        },
        {
            "current": 2565.481,
            "min": 800.0,
            "max": 5500.0
        },
        {
            "current": 2978.058,
            "min": 800.0,
            "max": 5500.0
        },
        {
            "current": 800.0,
            "min": 800.0,
            "max": 5800.0
        },
        {
            "current": 4134.765,
            "min": 800.0,
            "max": 5800.0
        },
        {
            "current": 5038.268,
            "min": 800.0,
            "max": 5800.0
        },
        {
            "current": 800.0,
            "min": 800.0,
            "max": 5800.0
        },
        {
            "current": 1775.3,
            "min": 800.0,
            "max": 5500.0
        },
        {
            "current": 4456.39,
            "min": 800.0,
            "max": 5500.0
        },
        {
            "current": 1353.11,
            "min": 800.0,
            "max": 5500.0
        },
        {
            "current": 800.0,
            "min": 800.0,
            "max": 5500.0
        },
        {
            "current": 800.0,
            "min": 800.0,
            "max": 4300.0
        },
        {
            "current": 2462.672,
            "min": 800.0,
            "max": 4300.0
        },
        {
            "current": 800.0,
            "min": 800.0,
            "max": 4300.0
        },
        {
            "current": 800.0,
            "min": 800.0,
            "max": 4300.0
        },
        {
            "current": 2081.119,
            "min": 800.0,
            "max": 4300.0
        },
        {
            "current": 800.0,
            "min": 800.0,
            "max": 4300.0
        },
        {
            "current": 800.0,
            "min": 800.0,
            "max": 4300.0
        },
        {
            "current": 800.0,
            "min": 800.0,
            "max": 4300.0
        },
        {
            "current": 800.0,
            "min": 800.0,
            "max": 4300.0
        },
        {
            "current": 4022.98,
            "min": 800.0,
            "max": 4300.0
        },
        {
            "current": 800.0,
            "min": 800.0,
            "max": 4300.0
        },
        {
            "current": 1287.455,
            "min": 800.0,
            "max": 4300.0
        },
        {
            "current": 800.0,
            "min": 800.0,
            "max": 4300.0
        },
        {
            "current": 800.0,
            "min": 800.0,
            "max": 4300.0
        },
        {
            "current": 800.0,
            "min": 800.0,
            "max": 4300.0
        },
        {
            "current": 800.0,
            "min": 800.0,
            "max": 4300.0
        }
    ],
    "disk": {
        "/": {
            "total": 365.6147689819336,
            "used": 118.34900283813477
        }
    },
    "memory": {
        "total": 125.61077117919922
    }
}
